{
    "intents": [
        {
            "tag": "greeting",
            "patterns": [
                "Hi",
                "Hey",
                "Guten Tag",
                "Hallo",
                "Gruesse",
                "Gegruesst",
                "Hey, wie gehts?"
            ],
            "responses": [
                "Guten Tag",
                "Hallo",
                "Sehr gut, danke!"
            ]
        },
        {
            "tag": "goodbye",
            "patterns": [
                "Tschuess",
                "Ciao",
                "Auf Wiedersehen",
                "Auf Wiederhoeren"
            ],
            "responses": [
                "Bis zum naechsten Mal!"
            ]
        },
        {
            "tag": "content",
            "patterns": [
                "xyz"
            ],
            "responses":[
                "abc"
            ]
        }
    ]
}